box_chunked_upload_tool.py
box_folder_upload_tool.py
box_share_link_tool.py
mcp_server_box.py
mcp_server_box-0.1.2.dist-info/METADATA
mcp_server_box-0.1.2.dist-info/WHEEL
mcp_server_box-0.1.2.dist-info/entry_points.txt
mcp_server_box-0.1.2.dist-info/RECORD
