Metadata-Version: 2.4
Name: mcp-server-box
Version: 0.1.2
Summary: Add your description here
Requires-Python: >=3.13
Requires-Dist: box-ai-agents-toolkit>=0.0.42
Requires-Dist: box-sdk-gen>=1.13.0
Requires-Dist: mcp[cli]>=1.6.0
Requires-Dist: python-dotenv>=1.1.0
